llm_tasker/backends/redis/queue.py
llm_tasker/backends/redis/worker.py
llm_tasker/exceptions.py
llm_tasker/parser.py
llm_tasker/queue.py
llm_tasker/task.py
llm_tasker-0.1.2.dist-info/LICENSE
llm_tasker-0.1.2.dist-info/WHEEL
llm_tasker-0.1.2.dist-info/METADATA
llm_tasker-0.1.2.dist-info/RECORD
