Metadata-Version: 2.1
Name: llm-tasker
Version: 0.1.2
Summary: A lightweight Python library for creating tasks and workflows with Large Language Models (LLMs) using prompt templates.
Home-page: https://github.com/nikirg/llm_task
License: MIT
Author: Nikita Irgashev
Author-email: nik.irg@yandex.ru
Requires-Python: >=3.11,<4.0
Classifier: License :: OSI Approved :: MIT License
Classifier: Programming Language :: Python :: 3
Classifier: Programming Language :: Python :: 3.11
Requires-Dist: openai (>=1.51.0,<2.0.0)
Requires-Dist: pydantic (>=2.9.2,<3.0.0)
Project-URL: Documentation, https://github.com/nikirg/llm_task
Project-URL: Repository, https://github.com/nikirg/llm_task
